SwiftGUI_Matplot/__init__.py
SwiftGUI_Matplot/GlobalOptions.py
SwiftGUI_Matplot/Matplot.py
swiftgui_matplot-0.1.2.dist-info/LICENSE
swiftgui_matplot-0.1.2.dist-info/METADATA
swiftgui_matplot-0.1.2.dist-info/WHEEL
swiftgui_matplot-0.1.2.dist-info/RECORD
