Metadata-Version: 2.3
Name: SwiftGUI_Matplot
Version: 0.1.2
Summary: An integration of matplotlib-figures into SwiftGUI
License: Apache-2.0
Author: Eric aka CheesecakeTV
Author-email: cheesecaketv53+pypi@gmail.com
Requires-Python: >=3.10
Classifier: Programming Language :: Python :: 3
Classifier: Operating System :: OS Independent
Requires-Dist: SwiftGUI
Requires-Dist: matplotlib
Project-URL: Documentation, https://github.com/CheesecakeTV/SwiftGUI-Docs
Project-URL: Repository, https://github.com/CheesecakeTV/SwiftGUI-Matplot
Project-URL: issues, https://github.com/CheesecakeTV/SwiftGUI/issues
